{
  "id": "pageheader",
  "type": "SharedSlice",
  "name": "Pageheader",
  "description": "Pageheader",
  "variations": [
    {
      "id": "default",
      "name": "Default",
      "docURL": "...",
      "version": "initial",
      "description": "Default",
      "imageUrl": "",
      "primary": {
        "headline": {
          "type": "StructuredText",
          "config": {
            "label": "Headline",
            "placeholder": "",
            "allowTargetBlank": false,
            "single": "heading1"
          }
        }
      },
      "items": {}
    }
  ]
}